test_generator/__init__.py
test_generator/core.py
test_generator/views.py
test_generator/viewsets.py
django_test_generator-0.6.1.dist-info/LICENSE
django_test_generator-0.6.1.dist-info/METADATA
django_test_generator-0.6.1.dist-info/WHEEL
django_test_generator-0.6.1.dist-info/top_level.txt
django_test_generator-0.6.1.dist-info/RECORD
